{
  "users": [
    {
      "id": 1,
      "name": "Joe",
      "password": "123",
      "favorites": []
    },
    {
      "id": 2,
      "name": "Nils",
      "password": "123",
      "favorites": []
    },
    {
      "id": 3,
      "name": "Adam",
      "password": "123",
      "favorites": []
    },
    {
      "id": 4,
      "name": "Grace",
      "password": "123",
      "favorites": [
        {
          "id": 564263,
          "sol": 1360,
          "camera": {
            "id": 21,
            "name": "RHAZ",
            "rover_id": 5,
            "full_name": "Rear Hazard Avoidance Camera"
          },
          "img_src": "http://mars.jpl.nasa.gov/msl-raw-images/proj/msl/redops/ods/surface/sol/01360/opgs/edr/rcam/RLB_518226992EDR_F0542280RHAZ00323M_.JPG",
          "earth_date": "2016-06-03",
          "rover": {
            "id": 5,
            "name": "Curiosity",
            "landing_date": "2012-08-06",
            "launch_date": "2011-11-26",
            "status": "active"
          }
        }
      ]
    }
  ]
}